README.md
setup.cfg
setup.py
dyn2sel/__init__.py
dyn2sel/validation_set.py
dyn2sel.egg-info/PKG-INFO
dyn2sel.egg-info/SOURCES.txt
dyn2sel.egg-info/dependency_links.txt
dyn2sel.egg-info/requires.txt
dyn2sel.egg-info/top_level.txt
dyn2sel/apply_dcs/DESDDMethod.py
dyn2sel/apply_dcs/DPDESMethod.py
dyn2sel/apply_dcs/DYNSEMethod.py
dyn2sel/apply_dcs/MDEMethod.py
dyn2sel/apply_dcs/PDCESMethod.py
dyn2sel/apply_dcs/__init__.py
dyn2sel/apply_dcs/base.py
dyn2sel/dcs_techniques/__init__.py
dyn2sel/dcs_techniques/base.py
dyn2sel/dcs_techniques/desdd_selection.py
dyn2sel/dcs_techniques/mde_selection.py
dyn2sel/dcs_techniques/rank.py
dyn2sel/dcs_techniques/extras/oracle.py
dyn2sel/dcs_techniques/from_deslib/a_posteriori.py
dyn2sel/dcs_techniques/from_deslib/a_priori.py
dyn2sel/dcs_techniques/from_deslib/deslib_interface.py
dyn2sel/dcs_techniques/from_deslib/knop.py
dyn2sel/dcs_techniques/from_deslib/knora_e.py
dyn2sel/dcs_techniques/from_deslib/knora_u.py
dyn2sel/dcs_techniques/from_deslib/lca.py
dyn2sel/dcs_techniques/from_deslib/mcb.py
dyn2sel/dcs_techniques/from_deslib/metades.py
dyn2sel/dcs_techniques/from_deslib/modified_rank.py
dyn2sel/dcs_techniques/from_deslib/ola.py
dyn2sel/ensemble/__init__.py
dyn2sel/ensemble/_skmultiflow_encapsulator.py
dyn2sel/ensemble/base.py
dyn2sel/ensemble/desdd_ensemble.py
dyn2sel/ensemble/dpdes_ensemble.py
dyn2sel/ensemble/dynse_ensemble.py
dyn2sel/ensemble/mde_ensemble.py
dyn2sel/ensemble/pdces_ensemble.py
dyn2sel/utils/__init__.py
dyn2sel/utils/balanced_accuracy.py
dyn2sel/utils/evaluators/__init__.py
dyn2sel/utils/evaluators/holdout.py
dyn2sel/utils/evaluators/prequential.py