Metadata-Version: 1.1
Name: dyn2sel
Version: 0.1.4
Summary: A framework for applying and implementing DCS techniques in the data stream mining context.
Home-page: https://github.com/luccaportes/Scikit-DYN2SEL
Author: Lucca Portes
Author-email: lucca54@gmail.com
License: MIT
Download-URL: https://github.com/luccaportes/Scikit-DYN2SEL/archive/v0.1.4.tar.gz
Keywords: Dynamic Selection,Machine Learning,Data Streams
Platform: UNKNOWN
Classifier: Development Status :: 3 - Alpha
Classifier: Intended Audience :: Developers
Classifier: Topic :: Software Development :: Build Tools
Classifier: License :: OSI Approved :: MIT License
Classifier: Programming Language :: Python :: 3
Classifier: Programming Language :: Python :: 3.4
Classifier: Programming Language :: Python :: 3.5
Classifier: Programming Language :: Python :: 3.6
Classifier: Programming Language :: Python :: 3.7
